{
  "realm" : "master",
  "users" : [ {
    "id" : "7d2608ec-c3c9-49bf-8bef-dca6d20e3352",
    "username" : "admin",
    "emailVerified" : false,
    "attributes" : {
      "is_temporary_admin" : [ "true" ]
    },
    "enabled" : true,
    "createdTimestamp" : 1764748232639,
    "totp" : false,
    "credentials" : [ {
      "id" : "cad73e26-514a-4693-8c6d-e739d06d7b1a",
      "type" : "password",
      "createdDate" : 1764748232711,
      "secretData" : "{\"value\":\"cXK2FJ1HzC7nnoqIELTUXRNTJ/W4PWyizFN2Nu8hxRM=\",\"salt\":\"+wK1RB/Xr+/mj3BZ98sMOw==\",\"additionalParameters\":{}}",
      "credentialData" : "{\"hashIterations\":5,\"algorithm\":\"argon2\",\"additionalParameters\":{\"hashLength\":[\"32\"],\"memory\":[\"7168\"],\"type\":[\"id\"],\"version\":[\"1.3\"],\"parallelism\":[\"1\"]}}"
    } ],
    "disableableCredentialTypes" : [ ],
    "requiredActions" : [ ],
    "realmRoles" : [ "default-roles-master", "admin" ],
    "notBefore" : 0,
    "groups" : [ ]
  } ]
}